crudal/__init__.py
crudal/base_async.py
crudal/base_sync.py
crudal/operations/__init__.py
crudal/operations/add.py
crudal/operations/base.py
crudal/operations/delete.py
crudal/operations/find.py
crudal/operations/update.py
crudal/types.py
crudal/utils.py
crudal-0.3.1.dist-info/METADATA
crudal-0.3.1.dist-info/WHEEL
crudal-0.3.1.dist-info/RECORD
