Metadata-Version: 2.1
Name: crudal
Version: 0.3.1
Summary: CRUD operations for SQLAlchemy models
License: MIT
Author: andrewsap
Author-email: andrewsapw@gmail.com
Requires-Python: >=3.8,<4.0
Classifier: License :: OSI Approved :: MIT License
Classifier: Programming Language :: Python :: 3
Classifier: Programming Language :: Python :: 3.8
Classifier: Programming Language :: Python :: 3.9
Classifier: Programming Language :: Python :: 3.10
Classifier: Programming Language :: Python :: 3.11
Requires-Dist: SQLAlchemy[asyncio] (>=2.0.7,<3.0.0)
